truckersmp_cli/__init__.py
truckersmp_cli/args.py
truckersmp_cli/configfile.py
truckersmp_cli/flatpak_helper.py
truckersmp_cli/gamestarter.py
truckersmp_cli/logger.py
truckersmp_cli/main.py
truckersmp_cli/proton.json
truckersmp_cli/steamcmd.py
truckersmp_cli/steamruntime.json
truckersmp_cli/steamruntime_helper.py
truckersmp_cli/truckersmp-cli.exe
truckersmp_cli/truckersmp.py
truckersmp_cli/utils.py
truckersmp_cli/variables.py
truckersmp_cli-0.10.2.1.data/scripts/truckersmp-cli
truckersmp_cli-0.10.2.1.dist-info/LICENSE
truckersmp_cli-0.10.2.1.dist-info/METADATA
truckersmp_cli-0.10.2.1.dist-info/WHEEL
truckersmp_cli-0.10.2.1.dist-info/top_level.txt
truckersmp_cli-0.10.2.1.dist-info/RECORD
