Metadata-Version: 2.1
Name: truckersmp-cli
Version: 0.10.2.1
Summary: A simple launcher for TruckersMP to be used with Wine/Proton
Home-page: https://github.com/truckersmp-cli/truckersmp-cli
License: MIT
Project-URL: Bug Tracker, https://github.com/truckersmp-cli/truckersmp-cli/issues
Project-URL: Source Code, https://github.com/truckersmp-cli/truckersmp-cli
Platform: x86_64 POSIX systems
Classifier: Development Status :: 3 - Alpha
Classifier: Intended Audience :: End Users/Desktop
Classifier: License :: OSI Approved :: MIT License
Classifier: Programming Language :: Python
Classifier: Programming Language :: Python :: 3
Classifier: Programming Language :: Python :: 3 :: Only
Classifier: Topic :: Games/Entertainment
Classifier: Topic :: Games/Entertainment :: Simulation
Requires-Python: >=3.6
License-File: LICENSE
Provides-Extra: optional
Requires-Dist: setuptools ; extra == 'optional'
Requires-Dist: vdf ; extra == 'optional'
